Módulos/unidade_controle.v
/*
 =================================================================
 Módulo da Unidade de Controle Principal ("CEO")
 =================================================================
*/
module Unidade_Controle_Principal (
    input  [6:0] opcode,
    output reg    RegWrite,
    output reg    ALUSrc,
    output reg    MemToReg,
    output reg    MemRead,
    output reg    MemWrite,
    output reg    Branch,
    output reg [1:0] ALUOp
);

    always @(*) begin
        // Valores padrão seguros
        RegWrite = 1'b0; ALUSrc = 1'b0; MemToReg = 1'b0; MemRead  = 1'b0;
        MemWrite = 1'b0; Branch = 1'b0; ALUOp    = 2'bxx;

        case (opcode)
            // Tipo-R (sub, or, srl)
            7'b0110011: begin
                RegWrite = 1'b1; ALUOp = 2'b10; // ALUOp '10' = Usar Functs
            end
            // Tipo-I Load (lh)
            7'b0000011: begin
                RegWrite = 1'b1; ALUSrc = 1'b1; MemToReg = 1'b1; MemRead = 1'b1; ALUOp = 2'b00; // ALUOp '00' = SOMA
            end
            // Tipo-I Imediato (andi)
            7'b0010011: begin
                RegWrite = 1'b1; ALUSrc = 1'b1; ALUOp = 2'b11; // ALUOp '11' = AND
            end
            // Tipo-S Store (sh)
            7'b0100011: begin
                ALUSrc = 1'b1; MemWrite = 1'b1; ALUOp = 2'b00; // ALUOp '00' = SOMA
            end
            // Tipo-B Branch (beq)
            7'b1100011: begin
                Branch = 1'b1; ALUOp = 2'b01; // ALUOp '01' = SUB
            end
        endcase
    end
endmodule


/*
 =================================================================
 Módulo da Unidade de Controle da ULA ("Gerente Especialista")
 =================================================================
*/
module Unidade_Controle_ULA (
    input  [1:0]  ALUOp,
    input  [6:0]  funct7,
    input  [2:0]  funct3,
    output reg [3:0]  alu_control_out
);
    localparam ALU_AND = 4'b0000, ALU_OR  = 4'b0001, ALU_ADD = 4'b0010, ALU_SUB = 4'b0100, ALU_SRL = 4'b0101;

    always @(*) begin
        case (ALUOp)
            2'b00: alu_control_out = ALU_ADD; // Comando direto para SOMA
            2'b01: alu_control_out = ALU_SUB; // Comando direto para SUB
            2'b11: alu_control_out = ALU_AND; // Comando direto para AND
            2'b10: begin // Comando para decodificar Tipo-R
                case (funct3)
                    3'b000: begin // ADD ou SUB
                        if (funct7 == 7'b0100000) alu_control_out = ALU_SUB; // sub
                        else alu_control_out = ALU_ADD; // add
                    end
                    3'b110: alu_control_out = ALU_OR;   // or
                    3'b101: alu_control_out = ALU_SRL;  // srl
                    default: alu_control_out = 4'hX;
                endcase
            end
            default: alu_control_out = 4'hX;
        endcase
    end
endmodule

Módulos/memoria_dados.v
/*
 Módulo da Memória de Dados.
 Armazena os dados do programa.
 Realiza leituras de forma combinacional e escritas de forma síncrona.
*/
module Memoria_Dados (
    input         clock,
    input         MemWrite,      // Sinal que habilita a escrita
    input         MemRead,       // Sinal que habilita a leitura
    input  [31:0] address,       // Endereço vindo da ULA
    input  [31:0] write_data,    // Dado a ser escrito (vindo de rs2)
    output [31:0] read_data      // Dado lido da memória
);

    // Declaração da memória. Ex: 1024 posições de 32 bits.
    // Em um sistema real, seria muito maior.
    reg [31:0] data_memory [1023:0];

    // Lógica de Leitura: Combinacional.
    // Se MemRead estiver ativo, a saída recebe o valor da posição de memória.
    // Senão, a saída fica indefinida (alta impedância).
    assign read_data = data_memory[address[11:2]];


    // Lógica de Escrita: Síncrona.
    // Ocorre na borda de subida do clock.
    always @(posedge clock)
    begin
        // Só escreve se o sinal 'MemWrite' estiver ativo.
        if (MemWrite) 
        begin
            data_memory[address[11:2]] <= write_data;
        end
    end

endmodule

Módulos/ula.v
module ULA (
    input  [31:0] in1, in2, 
    input  [3:0]  ula_control,
    output reg [31:0] ula_result,
    output reg        zero_flag
);

    always @(*)
    begin
        // Bloco case para selecionar a operação
        case(ula_control)
            4'b0000: ula_result = in1 & in2;  // AND
            4'b0001: ula_result = in1 | in2;  // OR
            4'b0010: ula_result = in1 + in2;  // ADD
            4'b0100: ula_result = in1 - in2;  // SUB
            4'b0101: ula_result = in1 >> in2;  // SRL
            4'b0011: ula_result = in1 << in2;  // SLL (extra)
            4'b0110: ula_result = in1 * in2;  // Multiply (extra)
            4'b0111: ula_result = in1 ^ in2;  // XOR (extra)
            4'b1000: begin                   // SLT (extra)
                if(in1 < in2)
                    ula_result = 32'd1;
                else
                    ula_result = 32'd0;
            end
            default: ula_result = 32'hxxxxxxxx; // Saída indefinida para controle inválido
        endcase

        // Lógica para a flag 'zero', fora do case
        if (ula_result == 32'd0)
            zero_flag = 1'b1;
        else
            zero_flag = 1'b0;
    end

endmodule

Módulos/banco_registradores.v
/*
 Módulo do Banco de Registradores (Register File) - VERSÃO FINAL CORRIGIDA
 Com lógica de reset assíncrono padrão.
*/
module REG_FILE(
    input  [4:0]  read_reg_num1,
    input  [4:0]  read_reg_num2,
    input  [4:0]  write_reg,
    input  [31:0] write_data,
    output [31:0] read_data1,
    output [31:0] read_data2,
    input         regwrite,
    input         clock,
    input         reset
);

    reg [31:0] reg_memory [0:31];
    integer i;

    // Lógica de Leitura Combinacional (continua correta)
    assign read_data1 = (read_reg_num1 == 5'b0) ? 32'b0 : reg_memory[read_reg_num1];
    assign read_data2 = (read_reg_num2 == 5'b0) ? 32'b0 : reg_memory[read_reg_num2];

    // --- CORREÇÃO: Lógica de escrita e reset UNIFICADA E SÍNCRONA ---
    always @(posedge clock or posedge reset)
    begin
        // Se o reset for ativado (reset == 1), inicializa os registradores
        if (reset) begin
            // Usando um loop para inicializar, é mais limpo
            for (i=0; i<32; i=i+1) begin
                reg_memory[i] <= i;
            end
        end
        // Senão, é um ciclo de clock normal
        else begin
            // E a lógica de escrita normal é executada
            if (regwrite && (write_reg != 5'b0)) begin
                reg_memory[write_reg] <= write_data;
            end
        end
    end

endmodule

Módulos/memoria_instrucao.v
// /*
//  Módulo da Memória de Instrução (ROM).
//  Armazena as instruções do programa a ser executado.
//  O conteúdo é carregado a partir de um arquivo externo no início da simulação.
// */
// module Memoria_Instrucao (
//     input  [31:0] address,       // Endereço vindo do PC
//     output [31:0] instruction    // Instrução de 32 bits lida da memória
// );

//     // Declaração da memória. Ex: 256 posições de 32 bits.
//     // O tamanho pode ser ajustado conforme a necessidade do programa.
//     reg [31:0] rom_memory [0:255];

//     // -- O "Pulo do Gato": Carregando o Programa --
//     // Este bloco 'initial' é executado apenas UMA VEZ no início da simulação.
//     // O comando $readmemh lê o arquivo "programa.hex" e carrega seu conteúdo
//     // para dentro da nossa 'rom_memory'.
//     initial begin
//         $readmemh("programa.hex", rom_memory);
//     end

//     // Lógica de Leitura: Combinacional.
//     // O endereço do PC é um endereço de byte, mas nossa memória é um array de
//     // palavras de 32 bits (4 bytes). Por isso, ignoramos os 2 bits menos
//     // significativos do endereço para selecionar a palavra correta.
//     assign instruction = rom_memory[address[9:2]]; // Usamos [9:2] para 256 palavras.

// endmodule

/*
 Módulo da Memória de Instrução (ROM) - VERSÃO DE DEPURAÇÃO
 O programa está "hardcoded" para garantir o carregamento correto.
*/
module Memoria_Instrucao (
    input  [31:0] address,
    output [31:0] instruction
);

    reg [31:0] rom_memory [0:255];

    // -- DEBUG: Carregando o programa diretamente na memória --
    initial begin
        // Comentamos a linha que lê o arquivo externo
        // $readmemh("programa.hex", rom_memory); 

        // E colocamos os valores na mão
        rom_memory[0] = 32'h00001503; // 0x00: lh x10, 0(x0)
        rom_memory[1] = 32'h00401583; // 0x04: lh x11, 4(x0)
        rom_memory[2] = 32'h40b50633; // 0x08: sub x12, x10, x11
        rom_memory[3] = 32'h00b566b3; // 0x0C: or x13, x10, x11
        rom_memory[4] = 32'h00857713; // 0x10: andi x14, x10, 8
        rom_memory[5] = 32'h001557b3; // 0x14: srl x15, x10, 1
        rom_memory[6] = 32'h00a70263; // 0x18: beq x14, x10, 4
        rom_memory[7] = 32'h00c02423; // 0x1C: sh x12, 8(x0)
        rom_memory[8] = 32'h00000063; // 0x20: beq x0, x0, 0
    end

    assign instruction = rom_memory[address[9:2]];

endmodule

Módulos/processador.v
/*
 Módulo Top-Level do Processador RISC-V Monociclo.
 Grupo 12: lh, sh, sub, or, andi, srl, beq
 CORRIGIDO E REVISADO
*/
module processador(
    input clock,
    input reset
);

    // =================================================================
    // --- 1. FIOS (WIRES) E REGISTRADORES (REGS) ---
    // =================================================================
    
    // -- Sinais de Controle
    wire        w_RegWrite, w_ALUSrc, w_MemToReg, w_MemRead, w_MemWrite, w_Branch;
    wire [1:0]  w_ALUOp;
    wire [3:0]  w_Final_ALU_Control;

    // -- Barramentos de Dados
    // ****** CORREÇÃO 1: w_pc_current agora é um REGISTRADOR ******
    reg  [31:0] w_pc_current;
    wire [31:0] w_pc_next, w_pc_plus_4, w_pc_branch_target;
    // ***************************************************************
    
    wire [31:0] w_instruction;
    wire [31:0] w_read_data_1, w_read_data_2;
    wire [31:0] w_immediate_extended;
    wire [31:0] w_alu_input_2;
    wire [31:0] w_alu_result;
    wire        w_alu_zero_flag;
    wire [31:0] w_mem_read_data;
    wire [31:0] w_write_data_to_regfile;
    
    // --- Fatiamento da Instrução
    wire [6:0] opcode = w_instruction[6:0];
    wire [4:0] rd     = w_instruction[11:7];
    wire [2:0] funct3 = w_instruction[14:12];
    wire [4:0] rs1    = w_instruction[19:15];
    wire [4:0] rs2    = w_instruction[24:20];
    wire [6:0] funct7 = w_instruction[31:25];


    // =================================================================
    // --- 2. CAMINHO DE DADOS (INSTÂNCIAS DOS MÓDULOS) ---
    // =================================================================

    // --- Estágio IF: Busca de Instrução ---
    
    // Registrador do PC
    always @(posedge clock or posedge reset) begin
        if (reset)
            w_pc_current <= 32'b0;
        else
            w_pc_current <= w_pc_next;
    end

    // Memória de Instrução (Modelada como ROM, precisa ser pré-carregada no testbench)
    Memoria_Instrucao u_imem (
        .address(w_pc_current), 
        .instruction(w_instruction)
    );

    // Lógica de cálculo do próximo PC
    assign w_pc_plus_4 = w_pc_current + 32'd4;
    assign w_pc_branch_target = w_pc_current + w_immediate_extended;
    assign w_pc_next = (w_Branch & w_alu_zero_flag) ? w_pc_branch_target : w_pc_plus_4;
    
    // --- Estágio ID: Decodificação e Banco de Registradores ---

    // Instância do Banco de Registradores
    REG_FILE u_regfile (
        .clock(clock), .reset(reset),
        .regwrite(w_RegWrite),
        .read_reg_num1(rs1),
        .read_reg_num2(rs2),
        .write_reg(rd),
        .write_data(w_write_data_to_regfile),
        .read_data1(w_read_data_1),
        .read_data2(w_read_data_2)
    );

    // Unidade de Extensão de Sinal
    assign w_immediate_extended = (opcode == 7'b0100011) ? {{20{w_instruction[31]}}, w_instruction[31:25], w_instruction[11:7]} : // Tipo-S (sh)
                                 (opcode == 7'b1100011) ? {{20{w_instruction[31]}}, w_instruction[7], w_instruction[30:25], w_instruction[11:8], 1'b0} : // Tipo-B (beq)
                                 {{20{w_instruction[31]}}, w_instruction[31:20]}; // Tipo-I (lh, andi)
    
    // --- Estágio EX: Execução ---

    // MUX para a segunda entrada da ULA
    assign w_alu_input_2 = w_ALUSrc ? w_immediate_extended : w_read_data_2;

    // ****** CORREÇÃO 2: Nomes das portas da ULA corrigidos ******
    ULA u_alu (
        .in1(w_read_data_1),
        .in2(w_alu_input_2),
        .ula_control(w_Final_ALU_Control),
        .ula_result(w_alu_result),
        .zero_flag(w_alu_zero_flag)
    );
    // **********************************************************
    
    // --- Estágio MEM: Acesso à Memória ---

    // Instância da Memória de Dados
    Memoria_Dados u_dmem (
        .clock(clock),
        .MemWrite(w_MemWrite),
        .MemRead(w_MemRead),
        .address(w_alu_result),
        .write_data(w_read_data_2),
        .read_data(w_mem_read_data)
    );

    // --- Estágio WB: Escrita de Volta ---

    // MUX final que escolhe o dado a ser escrito no registrador
    assign w_write_data_to_regfile = w_MemToReg ? w_mem_read_data : w_alu_result;

    // =================================================================
    // --- 3. UNIDADE DE CONTROLE (INSTÂNCIAS) ---
    // =================================================================

    // Instância da Unidade de Controle Principal
    Unidade_Controle_Principal u_main_control (
        .opcode(opcode),
        .RegWrite(w_RegWrite),
        .ALUSrc(w_ALUSrc),
        .MemToReg(w_MemToReg),
        .MemRead(w_MemRead),
        .MemWrite(w_MemWrite),
        .Branch(w_Branch),
        .ALUOp(w_ALUOp)
    );
    
    // Instância da Unidade de Controle da ULA
    Unidade_Controle_ULA u_alu_control (
        .ALUOp(w_ALUOp),
        .funct7(funct7),
        .funct3(funct3),
        .alu_control_out(w_Final_ALU_Control)
    );

endmodule

Módulos/testbench.v
`timescale 1ns/1ps

module testbench;

    reg clock;
    reg reset;
    integer i;

    // Instancia o nosso processador
    processador DUT (
        .clock(clock),
        .reset(reset)
    );

    // Geração do Clock
    initial begin
        clock = 0;
        forever #10 clock = ~clock; // Período de 20ns
    end

    // Controle da Simulação e Inicialização
    initial begin
        $dumpfile("waveform.vcd");
        $dumpvars(0, DUT);

        $display("\nIniciando simulacao do processador RISC-V - Grupo 12");
        $display("Instrucoes suportadas: lh, sh, sub, or, andi, srl, beq\n");

        // 1. Aplica o reset
        reset = 1;
        #15;
        reset = 0;

        // 2. ***** A CORREÇÃO CRÍTICA ESTÁ AQUI *****
        // Inicializa a Memória de Dados diretamente a partir do Testbench
        $display("--- INICIALIZANDO MEMORIA DE DADOS ---");
        DUT.u_dmem.data_memory[0] = 32'd10; // Força o valor 10 no endereço 0
        DUT.u_dmem.data_memory[1] = 32'd3;  // Força o valor 3 no endereço 4 (índice de palavra 1)
        
        // 3. Monitora a execução do programa
        $monitor("Time=%0t ns | PC=0x%h | Instr=0x%h", $time, DUT.w_pc_current, DUT.w_instruction);

        // 4. Roda a simulação por tempo suficiente e exibe o estado final
        #200;

        $display("\n================ ESTADO FINAL ================");
        $display("\n--- Registradores ---");
        for (i=0; i<32; i=i+4) begin
            $display("x%02d: 0x%h    x%02d: 0x%h    x%02d: 0x%h    x%02d: 0x%h",
                i, DUT.u_regfile.reg_memory[i], i+1, DUT.u_regfile.reg_memory[i+1],
                i+2, DUT.u_regfile.reg_memory[i+2], i+3, DUT.u_regfile.reg_memory[i+3]);
        end

        $display("\n--- Memoria de Dados (enderecos 0-36) ---");
        for (i=0; i<10; i=i+1) begin
            $display("Mem[%d]: 0x%h", i*4, DUT.u_dmem.data_memory[i]);
        end

        $display("\n--- Flags ---");
        $display("Zero Flag: %b", DUT.w_alu_zero_flag);
        $display("==========================================");

        $finish; // Encerra a simulação
    end

endmodule

Módulos/dump.vcd
$date
	Fri Aug 08 17:44:24 2025
$end
$version
	Icarus Verilog
$end
$timescale
	1ps
$end
$scope module testbench $end
$scope module DUT $end
$var wire 1 ! clock $end
$var wire 1 " reset $end
$var wire 32 # w_write_data_to_regfile [31:0] $end
$var wire 32 $ w_read_data_2 [31:0] $end
$var wire 32 % w_read_data_1 [31:0] $end
$var wire 32 & w_pc_plus_4 [31:0] $end
$var wire 32 ' w_pc_next [31:0] $end
$var wire 32 ( w_pc_branch_target [31:0] $end
$var wire 32 ) w_mem_read_data [31:0] $end
$var wire 32 * w_instruction [31:0] $end
$var wire 32 + w_immediate_extended [31:0] $end
$var wire 1 , w_alu_zero_flag $end
$var wire 32 - w_alu_result [31:0] $end
$var wire 32 . w_alu_input_2 [31:0] $end
$var wire 1 / w_RegWrite $end
$var wire 1 0 w_MemWrite $end
$var wire 1 1 w_MemToReg $end
$var wire 1 2 w_MemRead $end
$var wire 4 3 w_Final_ALU_Control [3:0] $end
$var wire 1 4 w_Branch $end
$var wire 1 5 w_ALUSrc $end
$var wire 2 6 w_ALUOp [1:0] $end
$var wire 5 7 rs2 [4:0] $end
$var wire 5 8 rs1 [4:0] $end
$var wire 5 9 rd [4:0] $end
$var wire 7 : opcode [6:0] $end
$var wire 7 ; funct7 [6:0] $end
$var wire 3 < funct3 [2:0] $end
$var reg 32 = w_pc_current [31:0] $end
$scope module u_alu $end
$var wire 32 > in2 [31:0] $end
$var wire 4 ? ula_control [3:0] $end
$var wire 32 @ in1 [31:0] $end
$var reg 32 A ula_result [31:0] $end
$var reg 1 , zero_flag $end
$upscope $end
$scope module u_alu_control $end
$var wire 3 B funct3 [2:0] $end
$var wire 7 C funct7 [6:0] $end
$var wire 2 D ALUOp [1:0] $end
$var parameter 4 E ALU_ADD $end
$var parameter 4 F ALU_AND $end
$var parameter 4 G ALU_OR $end
$var parameter 4 H ALU_SRL $end
$var parameter 4 I ALU_SUB $end
$var reg 4 J alu_control_out [3:0] $end
$upscope $end
$scope module u_dmem $end
$var wire 32 K address [31:0] $end
$var wire 1 ! clock $end
$var wire 32 L write_data [31:0] $end
$var wire 32 M read_data [31:0] $end
$var wire 1 0 MemWrite $end
$var wire 1 2 MemRead $end
$upscope $end
$scope module u_imem $end
$var wire 32 N address [31:0] $end
$var wire 32 O instruction [31:0] $end
$upscope $end
$scope module u_main_control $end
$var wire 7 P opcode [6:0] $end
$var reg 2 Q ALUOp [1:0] $end
$var reg 1 5 ALUSrc $end
$var reg 1 4 Branch $end
$var reg 1 2 MemRead $end
$var reg 1 1 MemToReg $end
$var reg 1 0 MemWrite $end
$var reg 1 / RegWrite $end
$upscope $end
$scope module u_regfile $end
$var wire 1 ! clock $end
$var wire 32 R read_data1 [31:0] $end
$var wire 32 S read_data2 [31:0] $end
$var wire 5 T read_reg_num1 [4:0] $end
$var wire 5 U read_reg_num2 [4:0] $end
$var wire 1 / regwrite $end
$var wire 1 " reset $end
$var wire 32 V write_data [31:0] $end
$var wire 5 W write_reg [4:0] $end
$var integer 32 X i [31:0] $end
$upscope $end
$upscope $end
$upscope $end
$enddefinitions $end
$comment Show the parameter values. $end
$dumpall
b100 I
b101 H
b1 G
b0 F
b10 E
$end
#0
$dumpvars
b0 X
b1010 W
bx V
b0 U
b0 T
b0 S
b0 R
b0 Q
b11 P
b1010100000011 O
b0 N
bx M
b0 L
b0 K
b10 J
b0 D
b0 C
b1 B
b0 A
b0 @
b10 ?
b0 >
b0 =
b1 <
b0 ;
b11 :
b1010 9
b0 8
b0 7
b0 6
15
04
b10 3
12
11
00
1/
b0 .
b0 -
1,
b0 +
b1010100000011 *
bx )
b0 (
b100 '
b100 &
b0 %
b0 $
bx #
1"
0!
$end
#10000
1!
#15000
0"
#20000
0!
#30000
0,
b100 -
b100 A
b100 K
b100 .
b100 >
b100 +
b100 $
b100 L
b100 S
b100 7
b100 U
b1011 9
b1011 W
b1000 '
b10000000001010110000011 *
b10000000001010110000011 O
b1000 &
b1000 (
b100 =
b100 N
1!
#40000
0!
#50000
b10000001011 +
bz )
bz M
bx .
bx >
bx -
bx A
bx K
b100 3
b100 ?
b100 J
b10 6
b10 D
b10 Q
02
01
05
1/
b100000 ;
b100000 C
bx $
bx L
bx S
b1011 7
b1011 U
bx %
bx @
bx R
b1010 8
b1010 T
b0 <
b0 B
b1100 9
b1100 W
b110011 :
b110011 P
b1100 '
b1000000101101010000011000110011 *
b1000000101101010000011000110011 O
b1100 &
b10000010011 (
b1000 =
b1000 N
1!
#60000
0!
#70000
b1011 +
b1 3
b1 ?
b1 J
b0 ;
b0 C
b110 <
b110 B
b1101 9
b1101 W
b10000 '
b101101010110011010110011 *
b101101010110011010110011 O
b10000 &
b10111 (
b1100 =
b1100 N
1!
#80000
0!
#90000
b0x000 #
b0x000 V
b1000 +
b0x000 -
b0x000 A
b0x000 K
b1000 .
b1000 >
b0 3
b0 ?
b0 J
15
b11 6
b11 D
b11 Q
1/
b1000 $
b1000 L
b1000 S
b1000 7
b1000 U
b111 <
b111 B
b1110 9
b1110 W
b10011 :
b10011 P
b10100 '
b100001010111011100010011 *
b100001010111011100010011 O
b10100 &
b11000 (
b10000 =
b10000 N
1!
#100000
0!
#110000
b0xxxxxxxxxxxxxxxxxxxxxxxxxxxxxxx #
b0xxxxxxxxxxxxxxxxxxxxxxxxxxxxxxx V
b1 +
b0xxxxxxxxxxxxxxxxxxxxxxxxxxxxxxx -
b0xxxxxxxxxxxxxxxxxxxxxxxxxxxxxxx A
b0xxxxxxxxxxxxxxxxxxxxxxxxxxxxxxx K
b1 .
b1 >
b101 3
b101 ?
b101 J
b10 6
b10 D
b10 Q
05
1/
b1 $
b1 L
b1 S
b1 7
b1 U
b101 <
b101 B
b1111 9
b1111 W
b110011 :
b110011 P
b11000 '
b101010101011110110011 *
b101010101011110110011 O
b11000 &
b10101 (
b10100 =
b10100 N
1!
#120000
0!
#130000
bx #
bx V
b100 +
bx .
bx >
bx -
bx A
bx K
b100 3
b100 ?
b100 J
14
b1 6
b1 D
b1 Q
0/
bx $
bx L
bx S
b1010 7
b1010 U
b0x000 %
b0x000 @
b0x000 R
b1110 8
b1110 T
b0 <
b0 B
b100 9
b100 W
b1100011 :
b1100011 P
b11100 '
b101001110000001001100011 *
b101001110000001001100011 O
b11100 &
b11100 (
b11000 =
b11000 N
1!
#140000
0!
#150000
b1000 #
b1000 V
b1000 -
b1000 A
b1000 K
b1000 .
b1000 >
b10 3
b10 ?
b10 J
b1000 +
10
15
b0 6
b0 D
b0 Q
04
b1100 7
b1100 U
b0 %
b0 @
b0 R
b0 8
b0 T
b10 <
b10 B
b1000 9
b1000 W
b100011 :
b100011 P
b100000 '
b110000000010010000100011 *
b110000000010010000100011 O
b100000 &
b100100 (
b11100 =
b11100 N
1!
#160000
0!
#170000
b0 #
b0 V
1,
b0 -
b0 A
b0 K
b0 .
b0 >
b100 3
b100 ?
b100 J
b0 +
14
b1 6
b1 D
b1 Q
00
05
b0 $
b0 L
b0 S
b0 7
b0 U
b0 <
b0 B
b0 9
b0 W
b1100011 :
b1100011 P
b100000 '
b1100011 *
b1100011 O
b100100 &
b100000 (
b100000 =
b100000 N
1!
